crystaldba/DEVELOPMENT.md
crystaldba/cli/Dockerfile
crystaldba/cli/README.md
crystaldba/cli/chat_loop.py
crystaldba/cli/chat_requester.py
crystaldba/cli/chat_response_followup.py
crystaldba/cli/chat_turn.py
crystaldba/cli/constants.py
crystaldba/cli/dba_chat_client.py
crystaldba/cli/keypair.py
crystaldba/cli/main.py
crystaldba/cli/parse_args.py
crystaldba/cli/profile.py
crystaldba/cli/sql_tool.py
crystaldba/cli/startup.py
crystaldba/cli/test/__init__.py
crystaldba/cli/test/e2e/__init__.py
crystaldba/cli/test/e2e/simple.py
crystaldba/cli/test/test_chat_loop.py
crystaldba/cli/test/test_chat_stepper.py
crystaldba/cli/test/test_dba_chat_client.py
crystaldba/cli/test/test_json_serialization.py
crystaldba/cli/test/test_main.py
crystaldba/cli/test/test_parse_args.py
crystaldba/cli/test/test_profile.py
crystaldba/cli/ui.py
crystaldba/shared/__init__.py
crystaldba/shared/api.py
crystaldba/shared/base64id.py
crystaldba/shared/base_sql_driver.py
crystaldba/shared/constants.py
crystaldba/shared/exceptions.py
crystaldba/shared/secure_session.py
crystaldba/shared/sql_serialization.py
crystaldba/shared/test/__init__.py
crystaldba/shared/test/conftest.py
crystaldba/shared/test/init.sql
crystaldba/shared/test/test_api.py
crystaldba/shared/test/test_base64id.py
crystaldba/shared/test/test_secure_session.py
crystaldba/shared/test/test_sql_serialization.py
crystaldba/shared/test/utils.py
tui/README.md
tui/__main__.py
tui/app.py
tui/constants.py
tui/models.py
tui/screens/chat_screen.py
tui/screens/help_screen.py
tui/time_display.py
tui/tui.scss
tui/widgets/agent_is_typing.py
tui/widgets/app_header.py
tui/widgets/chat.py
tui/widgets/chat_header.py
tui/widgets/chatbox.py
tui/widgets/prompt_input.py
tui/widgets/token_analysis.py
crystaldba-0.9.0.dist-info/METADATA
crystaldba-0.9.0.dist-info/WHEEL
crystaldba-0.9.0.dist-info/entry_points.txt
crystaldba-0.9.0.dist-info/RECORD
